domain_lang/__init__.py
domain_lang/admin.py
domain_lang/context_processors.py
domain_lang/middleware.py
domain_lang/models.py
domain_lang/tests.py
django_domain_language-0.0.2.dist-info/LICENSE
django_domain_language-0.0.2.dist-info/METADATA
django_domain_language-0.0.2.dist-info/WHEEL
django_domain_language-0.0.2.dist-info/top_level.txt
django_domain_language-0.0.2.dist-info/RECORD
